django_project_portfolio-1.3.1.dist-info/DESCRIPTION.rst
django_project_portfolio-1.3.1.dist-info/METADATA
django_project_portfolio-1.3.1.dist-info/RECORD
django_project_portfolio-1.3.1.dist-info/WHEEL
django_project_portfolio-1.3.1.dist-info/metadata.json
django_project_portfolio-1.3.1.dist-info/top_level.txt
projects/__init__.py
projects/admin.py
projects/apps.py
projects/managers.py
projects/models.py
projects/runtests.py
projects/urls.py
projects/views.py
projects/fixtures/projects.json
projects/migrations/0001_initial.py
projects/migrations/__init__.py
projects/tests/__init__.py
projects/tests/test_models.py
projects/tests/test_views.py
